accuralai_discord/__init__.py
accuralai_discord/analytics.py
accuralai_discord/bot.py
accuralai_discord/cli.py
accuralai_discord/config.py
accuralai_discord/context.py
accuralai_discord/context_aware.py
accuralai_discord/embeds.py
accuralai_discord/memory.py
accuralai_discord/multimodal.py
accuralai_discord/smart_history.py
accuralai_discord/streaming.py
accuralai_discord/test_bot.py
accuralai_discord/tools.py
accuralai_discord/utils.py
accuralai_discord/commands/__init__.py
accuralai_discord/commands/builtin.py
accuralai_discord/commands/registry.py
accuralai_discord/commands/slash.py
accuralai_discord/middleware/__init__.py
accuralai_discord/middleware/error_handler.py
accuralai_discord/middleware/rate_limit.py
accuralai_discord/test_bot/__init__.py
accuralai_discord/test_bot/__main__.py
accuralai_discord/test_bot/attachments.py
accuralai_discord/test_bot/chunking.py
accuralai_discord/test_bot/codebase_search.py
accuralai_discord/test_bot/embeddings.py
accuralai_discord/test_bot/web_search.py
accuralai_discord-0.2.1.dist-info/METADATA
accuralai_discord-0.2.1.dist-info/WHEEL
accuralai_discord-0.2.1.dist-info/entry_points.txt
accuralai_discord-0.2.1.dist-info/licenses/LICENSE
accuralai_discord-0.2.1.dist-info/RECORD
