Metadata-Version: 2.4
Name: accuralai-discord
Version: 0.2.1
Summary: AI-powered Discord bot package integrating AccuralAI orchestration.
Project-URL: homepage, https://accural-ai.web.app/
Project-URL: repository, https://github.com/AccuralAI/accuralai-discord
Project-URL: documentation, https://accuralai.readthedocs.io/en/latest/packages/accuralai-discord/index.html
Author: AccuralAI Maintainers
License: Apache-2.0
License-File: LICENSE
Requires-Python: >=3.10
Requires-Dist: accuralai-cache
Requires-Dist: accuralai-core
Requires-Dist: aiohttp>=3.9
Requires-Dist: discord-py>=2.3
Requires-Dist: pydantic>=2.5
Provides-Extra: dev
Requires-Dist: pytest; extra == 'dev'
Requires-Dist: pytest-anyio; extra == 'dev'
Requires-Dist: pytest-mock; extra == 'dev'
